{
  "replace": false,
  "values" : [
    {"required": false, "id": "ironchests:dirt_chest" },
    {"required": false, "id": "ironchests:copper_chest" },
    {"required": false, "id": "ironchests:iron_chest" },
    {"required": false, "id": "ironchests:gold_chest" },
    {"required": false, "id": "ironchests:diamond_chest" },
    {"required": false, "id": "ironchests:obsidian_chest" },
    {"required": false, "id": "ironchests:crystal_chest" },
    {"required": false, "id": "ironchests:netherite_chest" }
  ]
}